floatextras.py
floatextras-0.0.3.dist-info/DESCRIPTION.rst
floatextras-0.0.3.dist-info/METADATA
floatextras-0.0.3.dist-info/metadata.json
floatextras-0.0.3.dist-info/RECORD
floatextras-0.0.3.dist-info/top_level.txt
floatextras-0.0.3.dist-info/WHEEL
