Metadata-Version: 2.0
Name: floatextras
Version: 0.0.3
Summary: Extra functions on the built-in `float` similar to those on `Decimal`.
Home-page: https://github.com/abarnert/floatextras
Author: Andrew Barnert
Author-email: abarnert@yahoo.com
License: MIT
Keywords: float
Platform: UNKNOWN
Classifier: Development Status :: 4 - Beta
Classifier: License :: OSI Approved :: MIT License
Classifier: Intended Audience :: Developers
Classifier: Programming Language :: Python :: 3
